carrot/__init__.py
carrot/api.py
carrot/apps.py
carrot/consumer.py
carrot/exceptions.py
carrot/management/__init__.py
carrot/management/commands/__init__.py
carrot/management/commands/carrot.py
carrot/management/commands/carrot_daemon.py
carrot/management/commands/carrot_send.py
carrot/migrations/0001_initial.py
carrot/migrations/0002_add_task_name.py
carrot/migrations/0003_populate_task_name.py
carrot/migrations/0004_set_unique_task_name.py
carrot/migrations/__init__.py
carrot/mocks.py
carrot/models.py
carrot/objects.py
carrot/scheduler.py
carrot/static/carrot/axios.min.js
carrot/static/carrot/lodash.min.js
carrot/static/carrot/vue.min.js
carrot/static/carrot/vuetify.min.css
carrot/static/carrot/vuetify.min.js
carrot/static/carrot/vuex.min.js
carrot/static/carrot/white-carrot.png
carrot/templates/carrot/index.vue
carrot/test_carrot.py
carrot/tests.py
carrot/urls.py
carrot/utilities.py
carrot/views.py
django_carrot-1.5.0.dist-info/LICENSE
django_carrot-1.5.0.dist-info/WHEEL
django_carrot-1.5.0.dist-info/METADATA
django_carrot-1.5.0.dist-info/RECORD
