Metadata-Version: 2.1
Name: django-carrot
Version: 1.5.0
Summary: A RabbitMQ asynchronous task queue for Django.
Home-page: https://django-carrot.readthedocs.io
License: Apache-2.0
Author: Christoper Davies
Author-email: christopherdavies553@gmail.com
Requires-Python: >=3.6.3,<4.0.0
Classifier: Development Status :: 5 - Production/Stable
Classifier: Environment :: Web Environment
Classifier: Framework :: Django
Classifier: Framework :: Django :: 1.10
Classifier: Framework :: Django :: 1.11
Classifier: Framework :: Django :: 1.9
Classifier: Framework :: Django :: 2.0
Classifier: Intended Audience :: Developers
Classifier: License :: OSI Approved :: Apache Software License
Classifier: Operating System :: OS Independent
Classifier: Programming Language :: Python
Classifier: Programming Language :: Python :: 3
Classifier: Programming Language :: Python :: 3.5
Classifier: Programming Language :: Python :: 3.6
Classifier: Programming Language :: Python :: 3.7
Classifier: Topic :: Internet :: WWW/HTTP
Classifier: Topic :: Internet :: WWW/HTTP :: Dynamic Content
Requires-Dist: django (>=2.1,<3.0)
Requires-Dist: djangorestframework (>=3.9,<4.0)
Requires-Dist: json2html (>=1.2,<2.0)
Requires-Dist: pika (>=0.13.1,<0.14.0)
Requires-Dist: psutil (>=5.6,<6.0)
Requires-Dist: sphinx_bootstrap_theme (>=0.6.5,<0.7.0)
Project-URL: Repository, https://github.com/chris104957/django-carrot
